verbatim/__init__.py
verbatim/__main__.py
verbatim/_version.py
verbatim/config.py
verbatim/main.py
verbatim/models.py
verbatim/prefetch.py
verbatim/verbatim.py
verbatim/eval/__init__.py
verbatim/eval/cli.py
verbatim/eval/compare.py
verbatim/eval/find.py
verbatim/eval/diarizationlm/metrics.py
verbatim/eval/diarizationlm/utils.py
verbatim/transcript/__init__.py
verbatim/transcript/idprovider.py
verbatim/transcript/sentences.py
verbatim/transcript/transcript.py
verbatim/transcript/words.py
verbatim/transcript/postprocessing/config.py
verbatim/transcript/postprocessing/main.py
verbatim/transcript/postprocessing/processor.py
verbatim/transcript/postprocessing/utils.py
verbatim/voices/__init__.py
verbatim/voices/isolation.py
verbatim/voices/silences.py
verbatim/voices/transcribe/__init__.py
verbatim/voices/transcribe/faster_whisper.py
verbatim/voices/transcribe/transcribe.py
verbatim/voices/transcribe/whispercpp.py
verbatim/voices/transcribe/whispermlx.py
verbatim_audio/__init__.py
verbatim_audio/audio.py
verbatim_audio/convert.py
verbatim_audio/settings.py
verbatim_audio/sources/__init__.py
verbatim_audio/sources/audiosource.py
verbatim_audio/sources/factory.py
verbatim_audio/sources/ffmpegfileaudiosource.py
verbatim_audio/sources/fileaudiosource.py
verbatim_audio/sources/micaudiosource.py
verbatim_audio/sources/pcmaudiosource.py
verbatim_audio/sources/sourceconfig.py
verbatim_audio/sources/wavsink.py
verbatim_batch/__init__.py
verbatim_batch/__main__.py
verbatim_batch/main.py
verbatim_cli/__init__.py
verbatim_cli/args.py
verbatim_cli/config_file.py
verbatim_cli/configure.py
verbatim_cli/env.py
verbatim_cli/main.py
verbatim_cli/run_single.py
verbatim_diarization/__init__.py
verbatim_diarization/diarization.py
verbatim_diarization/policy.py
verbatim_diarization/prefetch.py
verbatim_diarization/utils.py
verbatim_diarization/channel/__init__.py
verbatim_diarization/channel/diarize.py
verbatim_diarization/diarize/__init__.py
verbatim_diarization/diarize/base.py
verbatim-1.2.2.dist-info/METADATA
verbatim-1.2.2.dist-info/WHEEL
verbatim-1.2.2.dist-info/entry_points.txt
verbatim-1.2.2.dist-info/licenses/LICENSE
verbatim-1.2.2.dist-info/RECORD
