Metadata-Version: 2.4
Name: verbatim
Version: 1.2.2
Summary: high quality multi-lingual speech to text
Project-URL: Homepage, https://github.com/gaspardpetit/verbatim
Author-email: Gaspard Petit <gaspardpetit@gmail.com>
License-Expression: MIT
License-File: LICENSE
Keywords: ASR,NLP,PyTorch,TensorFlow,audio analysis,audio processing,automatic speech recognition,deep learning,i18n,internationalization,language support,linguistics,machine learning,multilingual,natural language processing,speech analytics,speech-to-text,spoken language processing,text transcription,voice recognition
Classifier: Development Status :: 4 - Beta
Classifier: Intended Audience :: Developers
Classifier: License :: CC0 1.0 Universal (CC0 1.0) Public Domain Dedication
Classifier: Operating System :: OS Independent
Classifier: Programming Language :: Python :: 3
Classifier: Programming Language :: Python :: 3.10
Classifier: Programming Language :: Python :: 3.11
Classifier: Programming Language :: Python :: 3.12
Classifier: Topic :: Multimedia :: Sound/Audio :: Analysis
Classifier: Topic :: Multimedia :: Sound/Audio :: Speech
Classifier: Topic :: Scientific/Engineering :: Artificial Intelligence
Classifier: Topic :: Software Development :: Libraries :: Python Modules
Classifier: Topic :: Text Processing :: Linguistic
Requires-Python: <3.13,>=3.10
Requires-Dist: audio-separator>=0.40.0
Requires-Dist: av>=14.0.1
Requires-Dist: colorama>=0.4.6
Requires-Dist: dataclasses-json>=0.6.7
Requires-Dist: datasets>=3.2.0
Requires-Dist: demucs>=4.0.1
Requires-Dist: faster-whisper>=1.1.1
Requires-Dist: langcodes>=3.5.0
Requires-Dist: llvmlite>=0.44
Requires-Dist: mlx-whisper>=0.4.1; sys_platform == 'darwin'
Requires-Dist: numba>=0.61
Requires-Dist: numpy<3,>=2.2.2
Requires-Dist: onnxruntime<1.20,>=1.16.0
Requires-Dist: openai>=1.59.8
Requires-Dist: pillow==10.4.0
Requires-Dist: pyaudio>=0.2.14
Requires-Dist: pydub>=0.25.1
Requires-Dist: python-docx>=1.1.2
Requires-Dist: python-dotenv>=1.0.1
Requires-Dist: pywhispercpp>=1.3.0
Requires-Dist: pyyaml>=6.0.2
Requires-Dist: silero-vad>=5.1.2
Requires-Dist: sounddevice>=0.5.1
Requires-Dist: soundfile>=0.13.0
Requires-Dist: termcolor>=3.1.0
Requires-Dist: torch>=2.4.1
Requires-Dist: torchaudio>=2.4.1
Requires-Dist: wheel>=0.45.1
Requires-Dist: word-levenshtein>=0.0.3
Requires-Dist: wtpsplit>=2.1.2
Provides-Extra: cuda-gpu
Requires-Dist: onnxruntime-gpu<1.20,>=1.16.0; extra == 'cuda-gpu'
Provides-Extra: diarization
Requires-Dist: pyannote-audio[separation]>=4.0.2; extra == 'diarization'
Requires-Dist: pyannote-core==6.0.1; extra == 'diarization'
